killeraiagent/__init__.py
killeraiagent/kaia.py
killeraiagent/model.py
killeraiagent/resources.py
killeraiagent/setup_utils.py
killeraiagent-0.1.0.dist-info/licenses/LICENSE
killeraiagent-0.1.0.dist-info/METADATA
killeraiagent-0.1.0.dist-info/WHEEL
killeraiagent-0.1.0.dist-info/entry_points.txt
killeraiagent-0.1.0.dist-info/top_level.txt
killeraiagent-0.1.0.dist-info/RECORD
